notebook_parameterizer/__init__.py
notebook_parameterizer/cli.py
notebook_parameterizer/run.py
notebook_parameterizer-0.0.4.dist-info/LICENSE
notebook_parameterizer-0.0.4.dist-info/METADATA
notebook_parameterizer-0.0.4.dist-info/WHEEL
notebook_parameterizer-0.0.4.dist-info/entry_points.txt
notebook_parameterizer-0.0.4.dist-info/top_level.txt
notebook_parameterizer-0.0.4.dist-info/RECORD
