Metadata-Version: 2.1
Name: notebook-parameterizer
Version: 0.0.4
Summary: A tool to generate parameterized Jupyter Notebooks
Home-page: https://github.com/rasmunk/notebook_parameterizer
Author: Rasmus Munk
Author-email: rasmus.munk@nbi.ku.dk
License: MIT
Project-URL: Source Code, https://github.com/rasmunk/notebook_parameterizer
Keywords: jupyter notebook parameters
Platform: UNKNOWN
Classifier: Intended Audience :: Developers
Classifier: Intended Audience :: Science/Research
Classifier: License :: OSI Approved :: MIT License
Classifier: Programming Language :: Python
Classifier: Programming Language :: Python :: 3.6
Classifier: Programming Language :: Python :: 3.7
Classifier: Programming Language :: Python :: 3.8
Classifier: Programming Language :: Python :: 3.9
Requires-Dist: nbformat
Requires-Dist: papermill
Requires-Dist: click
Provides-Extra: dev
Requires-Dist: black (==20.8b1) ; extra == 'dev'
Requires-Dist: docutils (==0.16) ; extra == 'dev'
Requires-Dist: flake8 (==3.8.4) ; extra == 'dev'
Provides-Extra: test
Requires-Dist: pytest (==6.2.2) ; extra == 'test'
